ffffff/__init__.py
ffffff/_vendor/__init__.py
ffffff/_vendor/_black_version.py
ffffff/_vendor/appdirs.LICENSE.txt
ffffff/_vendor/appdirs.py
ffffff/_vendor/mypy_extensions.LICENSE
ffffff/_vendor/mypy_extensions.py
ffffff/_vendor/typing_extensions.LICENSE
ffffff/_vendor/typing_extensions.py
ffffff/_vendor/vendor.txt
ffffff/_vendor/black/LICENSE
ffffff/_vendor/black/__init__.py
ffffff/_vendor/black/__main__.py
ffffff/_vendor/black/py.typed
ffffff/_vendor/black_primer/cli.py
ffffff/_vendor/black_primer/lib.py
ffffff/_vendor/blackd/__init__.py
ffffff/_vendor/blib2to3/Grammar.txt
ffffff/_vendor/blib2to3/LICENSE
ffffff/_vendor/blib2to3/PatternGrammar.txt
ffffff/_vendor/blib2to3/__init__.py
ffffff/_vendor/blib2to3/pygram.py
ffffff/_vendor/blib2to3/pytree.py
ffffff/_vendor/blib2to3/pgen2/__init__.py
ffffff/_vendor/blib2to3/pgen2/conv.py
ffffff/_vendor/blib2to3/pgen2/driver.py
ffffff/_vendor/blib2to3/pgen2/grammar.py
ffffff/_vendor/blib2to3/pgen2/literals.py
ffffff/_vendor/blib2to3/pgen2/parse.py
ffffff/_vendor/blib2to3/pgen2/pgen.py
ffffff/_vendor/blib2to3/pgen2/token.py
ffffff/_vendor/blib2to3/pgen2/tokenize.py
ffffff/_vendor/click/LICENSE.rst
ffffff/_vendor/click/__init__.py
ffffff/_vendor/click/_bashcomplete.py
ffffff/_vendor/click/_compat.py
ffffff/_vendor/click/_termui_impl.py
ffffff/_vendor/click/_textwrap.py
ffffff/_vendor/click/_unicodefun.py
ffffff/_vendor/click/_winconsole.py
ffffff/_vendor/click/core.py
ffffff/_vendor/click/decorators.py
ffffff/_vendor/click/exceptions.py
ffffff/_vendor/click/formatting.py
ffffff/_vendor/click/globals.py
ffffff/_vendor/click/parser.py
ffffff/_vendor/click/termui.py
ffffff/_vendor/click/testing.py
ffffff/_vendor/click/types.py
ffffff/_vendor/click/utils.py
ffffff/_vendor/pathspec/LICENSE
ffffff/_vendor/pathspec/__init__.py
ffffff/_vendor/pathspec/compat.py
ffffff/_vendor/pathspec/pathspec.py
ffffff/_vendor/pathspec/pattern.py
ffffff/_vendor/pathspec/util.py
ffffff/_vendor/pathspec/patterns/__init__.py
ffffff-2020.8.31.dist-info/METADATA
ffffff-2020.8.31.dist-info/WHEEL
ffffff-2020.8.31.dist-info/entry_points.txt
ffffff-2020.8.31.dist-info/top_level.txt
ffffff-2020.8.31.dist-info/RECORD
