Metadata-Version: 2.1
Name: ffffff
Version: 2020.8.31
Summary: Black but single quotes
Home-page: https://github.com/grktsh/ffffff
License: UNKNOWN
Platform: UNKNOWN
Classifier: Development Status :: 4 - Beta
Classifier: Environment :: Console
Classifier: Intended Audience :: Developers
Classifier: License :: OSI Approved :: MIT License
Classifier: Operating System :: OS Independent
Classifier: Programming Language :: Python
Classifier: Programming Language :: Python :: 3.6
Classifier: Programming Language :: Python :: 3.7
Classifier: Programming Language :: Python :: 3.8
Classifier: Programming Language :: Python :: 3 :: Only
Classifier: Topic :: Software Development :: Quality Assurance
Requires-Python: >=3.6
Requires-Dist: regex (>=2020.1.8)
Requires-Dist: typed-ast (>=1.4.0)
Requires-Dist: dataclasses (>=0.6) ; python_version < "3.7"
